{
  "description": "Contains comprehensive metadata about a specific .NET major release, including support lifecycle information",
  "type": [
    "object",
    "null"
  ],
  "properties": {
    "kind": {
      "description": "Identifies the type of release or index document",
      "enum": [
        "index",
        "manifest",
        "major-release",
        "patch-release",
        "band",
        "content",
        "unknown"
      ]
    },
    "title": {
      "type": [
        "string",
        "null"
      ]
    },
    "_links": {
      "type": [
        "object",
        "null"
      ],
      "additionalProperties": {
        "description": "HAL\u002BJSON hypermedia link providing navigation to related resources",
        "type": [
          "object",
          "null"
        ],
        "properties": {
          "href": {
            "type": [
              "string",
              "null"
            ]
          },
          "relative": {
            "type": [
              "string",
              "null"
            ]
          },
          "title": {
            "type": [
              "string",
              "null"
            ]
          },
          "type": {
            "type": [
              "string",
              "null"
            ]
          }
        },
        "required": [
          "href"
        ]
      }
    },
    "version": {
      "type": [
        "string",
        "null"
      ]
    },
    "label": {
      "type": [
        "string",
        "null"
      ]
    },
    "lifecycle": {
      "description": "Lifecycle information for a .NET major release",
      "type": [
        "object",
        "null"
      ],
      "properties": {
        "release-type": {
          "enum": [
            "lts",
            "sts",
            null
          ]
        },
        "phase": {
          "description": "The support phases of a .NET release through its lifecycle",
          "enum": [
            "preview",
            "active",
            "maintenance",
            "eol"
          ]
        },
        "release-date": {
          "type": "string",
          "format": "date-time"
        },
        "eol-date": {
          "type": "string",
          "format": "date-time"
        },
        "supported": {
          "type": "boolean"
        }
      },
      "required": [
        "release-type",
        "phase",
        "release-date",
        "eol-date"
      ]
    },
    "_metadata": {
      "description": "Metadata about when and how this document was generated",
      "type": [
        "object",
        "null"
      ],
      "properties": {
        "generated-on": {
          "type": "string",
          "format": "date-time"
        },
        "generated-by": {
          "type": [
            "string",
            "null"
          ]
        }
      },
      "required": [
        "generated-on",
        "generated-by"
      ]
    }
  },
  "required": [
    "kind",
    "title",
    "_links",
    "version",
    "label"
  ]
}